Assemyaml-0.3.3.dist-info/DESCRIPTION.rst
Assemyaml-0.3.3.dist-info/METADATA
Assemyaml-0.3.3.dist-info/RECORD
Assemyaml-0.3.3.dist-info/WHEEL
Assemyaml-0.3.3.dist-info/entry_points.txt
Assemyaml-0.3.3.dist-info/metadata.json
Assemyaml-0.3.3.dist-info/top_level.txt
assemyaml/__init__.py
assemyaml/assemble.py
assemyaml/constructor.py
assemyaml/error.py
assemyaml/lambda_handler.py
assemyaml/loader.py
assemyaml/transclude.py
assemyaml/types.py
