Metadata-Version: 2.0
Name: Assemyaml
Version: 0.3.3
Summary: Assemble and merge multiple YAML documents
Home-page: http://assemyaml.nz/
Author: David Cuthbert
Author-email: dacut@kanga.org
License: Apache
Keywords: yaml
Platform: UNKNOWN
Classifier: Development Status :: 4 - Beta
Classifier: Intended Audience :: Developers
Classifier: License :: OSI Approved :: Apache Software License
Classifier: Programming Language :: Python
Classifier: Topic :: Software Development :: Libraries :: Python Modules
Classifier: Topic :: Text Processing
Requires-Dist: PyYAML (>=3.0)
Requires-Dist: boto3 (>=1.0)
Requires-Dist: six (>=1.10.0)
